[
  {
    "username": "joaosantos",
    "password": "joaosantos"
  },
  {
    "username": "Oscar Moraes",
    "password": "Oscar Moraes"
  },
  {
    "username": "ione Bettencourt",
    "password": "ione"
  },
  {
    "username": "Jose Sachilepa",
    "password": "Jose Sachilepa"
  },
  {
    "username": "Dario Lisboa",
    "password": "Dario Lisboa"
  },
  {
    "username": "Valdemar Capitango",
    "password": "Valdemar Capitango"
  },
  {
    "username": "Emidio Francisco",
    "password": "Emidio Francisco"
  },
  {
    "username": "Catarina Filho",
    "password": "Catarina Filho"
  },
  {
    "username": "Mariano Mangonga",
    "password": "Mariano Mangonga"
  },
  {
    "username": "Adolfo Kassissi",
    "password": "Adolfo Kassissi"
  },
  {
    "username": "Ermerson Costa",
    "password": "Ermerson Costa"
  },
  {
    "username": "Thalita Santos",
    "password": "Thalita Santos"
  },
  {
    "username": "Madalena Mbengue",
    "password": "Madalena Mbengue"
  },
  {
    "username": "Manuela Castelhano",
    "password": "Manuela Castelhano"
  }
]
